{
  "id": "56cb3c7b-a0cb-4cbd-9800-a6f6a3b32e27",
  "type": "page",
  "content": {
    "title": "Типология контейнерных площадок твердых коммунальных отходов"
  },
  "children": [
    {
      "id": "fe3278d6-0939-41f6-8134-a1a4d3dfc611",
      "type": "paragraph",
      "content": {
        "rich_text": [
          {
            "type": "text",
            "text": {
              "content": "На территории муниципального образования «город Екатеринбург» рекомендуется использовать контейнерные площадки 4 типов в зависимости от типов и условий застройки жилых районов",
              "link": null
            },
            "annotations": {
              "bold": false,
              "italic": false,
              "strikethrough": false,
              "underline": false,
              "code": false,
              "color": "default"
            },
            "plain_text": "На территории муниципального образования «город Екатеринбург» рекомендуется использовать контейнерные площадки 4 типов в зависимости от типов и условий застройки жилых районов",
            "href": null
          }
        ],
        "icon": null,
        "color": "default"
      },
      "children": []
    },
    {
      "id": 115,
      "type": "heading_1",
      "content": {
        "rich_text": [
          {
            "type": "text",
            "text": {
              "content": "Тип 1. Площадки с откатными контейнерами",
              "link": null
            },
            "annotations": {
              "bold": false,
              "italic": false,
              "strikethrough": false,
              "underline": false,
              "code": false,
              "color": "default"
            },
            "plain_text": "Тип 1. Площадки с откатными контейнерами",
            "href": null
          }
        ],
        "is_toggleable": false,
        "color": "default"
      },
      "children": []
    },
    {
      "id": "12a92f5e-6d61-48a4-8ea9-3da79db5156c",
      "type": "paragraph",
      "content": {
        "rich_text": [
          {
            "type": "text",
            "text": {
              "content": "Для установки на дворовых территориях сложившейся застройки Рекомендуемое соотношение контейнеров: 70 ",
              "link": null
            },
            "annotations": {
              "bold": false,
              "italic": false,
              "strikethrough": false,
              "underline": false,
              "code": false,
              "color": "default"
            },
            "plain_text": "Для установки на дворовых территориях сложившейся застройки Рекомендуемое соотношение контейнеров: 70 ",
            "href": null
          },
          {
            "type": "text",
            "text": {
              "content": "% контейнеров — для несортируемых отходов, 30 % — для сортируемых отходов",
              "link": null
            },
            "annotations": {
              "bold": false,
              "italic": false,
              "strikethrough": false,
              "underline": false,
              "code": false,
              "color": "default"
            },
            "plain_text": "% контейнеров — для несортируемых отходов, 30 % — для сортируемых отходов",
            "href": null
          }
        ],
        "icon": null,
        "color": "default"
      },
      "children": []
    },
    {
      "id": "8fce08ac-87ce-46a6-b7b9-1441df2f84b6",
      "type": "paragraph",
      "content": {
        "rich_text": [
          {
            "type": "text",
            "text": {
              "content": "Преимущества",
              "link": null
            },
            "annotations": {
              "bold": true,
              "italic": false,
              "strikethrough": false,
              "underline": false,
              "code": false,
              "color": "default"
            },
            "plain_text": "Преимущества",
            "href": null
          }
        ],
        "icon": null,
        "color": "default"
      },
      "children": []
    },
    {
      "type": "bulleted_list_folder",
      "children": [
        {
          "id": "d923667b-c5f5-46e7-b097-e3616a96e538",
          "type": "bulleted_list_item",
          "content": {
            "rich_text": [
              {
                "type": "text",
                "text": {
                  "content": "Экономичность",
                  "link": null
                },
                "annotations": {
                  "bold": false,
                  "italic": false,
                  "strikethrough": false,
                  "underline": false,
                  "code": false,
                  "color": "default"
                },
                "plain_text": "Экономичность",
                "href": null
              }
            ],
            "color": "default"
          },
          "children": []
        },
        {
          "id": "c03d1474-a147-458d-bcdf-dbdb4605c94b",
          "type": "bulleted_list_item",
          "content": {
            "rich_text": [
              {
                "type": "text",
                "text": {
                  "content": "Простота в обслуживании",
                  "link": null
                },
                "annotations": {
                  "bold": false,
                  "italic": false,
                  "strikethrough": false,
                  "underline": false,
                  "code": false,
                  "color": "default"
                },
                "plain_text": "Простота в обслуживании",
                "href": null
              }
            ],
            "color": "default"
          },
          "children": []
        }
      ]
    },
    {
      "id": "fd02ecfa-31e1-4543-9b5a-219b16f22569",
      "type": "paragraph",
      "content": {
        "rich_text": [],
        "icon": null,
        "color": "default"
      },
      "children": []
    },
    {
      "id": "abdc9147-2160-45ab-83fe-ee8704474a71",
      "type": "paragraph",
      "content": {
        "rich_text": [
          {
            "type": "text",
            "text": {
              "content": "Могут включать до 10 контейнеров. Возможна установка контейнера для опасных отходов.",
              "link": null
            },
            "annotations": {
              "bold": false,
              "italic": false,
              "strikethrough": false,
              "underline": false,
              "code": false,
              "color": "default"
            },
            "plain_text": "Могут включать до 10 контейнеров. Возможна установка контейнера для опасных отходов.",
            "href": null
          }
        ],
        "icon": null,
        "color": "default"
      },
      "children": []
    },
    {
      "id": "1b2e13fc-0312-4f77-b41b-0c08a90d163a",
      "type": "paragraph",
      "content": {
        "rich_text": [],
        "icon": null,
        "color": "default"
      },
      "children": []
    },
    {
      "id": "d4c323c7-f28d-4be0-9bc2-e04714ad28fa",
      "type": "paragraph",
      "content": {
        "rich_text": [
          {
            "type": "text",
            "text": {
              "content": "Габаритные размеры 7,0 × 1,5 м",
              "link": null
            },
            "annotations": {
              "bold": false,
              "italic": false,
              "strikethrough": false,
              "underline": false,
              "code": false,
              "color": "default"
            },
            "plain_text": "Габаритные размеры 7,0 × 1,5 м",
            "href": null
          }
        ],
        "icon": null,
        "color": "default"
      },
      "children": []
    },
    {
      "id": "adf9df15-43db-475d-9d97-aa4a3d8ec76f",
      "type": "image",
      "content": {
        "caption": [],
        "type": "file",
        "file": {
          "url": "/assets/adf9df15-43db-475d-9d97-aa4a3d8ec76f.webp"
        }
      },
      "children": []
    },
    {
      "id": "2d00b542-7645-4bb3-a339-242c884d4b72",
      "type": "paragraph",
      "content": {
        "rich_text": [],
        "icon": null,
        "color": "default"
      },
      "children": []
    },
    {
      "id": "6d08b115-55eb-4a7d-a4bb-2240a92bbb7b",
      "type": "paragraph",
      "content": {
        "rich_text": [
          {
            "type": "text",
            "text": {
              "content": "Габаритные размеры 8,5 × 1,5 м",
              "link": null
            },
            "annotations": {
              "bold": false,
              "italic": false,
              "strikethrough": false,
              "underline": false,
              "code": false,
              "color": "default"
            },
            "plain_text": "Габаритные размеры 8,5 × 1,5 м",
            "href": null
          }
        ],
        "icon": null,
        "color": "default"
      },
      "children": []
    },
    {
      "id": "21f9923b-d7c4-4cd6-852c-10e911b08b4f",
      "type": "image",
      "content": {
        "caption": [],
        "type": "file",
        "file": {
          "url": "/assets/21f9923b-d7c4-4cd6-852c-10e911b08b4f.webp"
        }
      },
      "children": []
    },
    {
      "id": "bc4d9f0c-172a-456b-be86-9cc124c5d29a",
      "type": "paragraph",
      "content": {
        "rich_text": [],
        "icon": null,
        "color": "default"
      },
      "children": []
    },
    {
      "id": "9dccffbd-ba88-4412-ba14-6468dbc2ac8a",
      "type": "paragraph",
      "content": {
        "rich_text": [
          {
            "type": "text",
            "text": {
              "content": "Габаритные размеры 12 × 1,5 м",
              "link": null
            },
            "annotations": {
              "bold": false,
              "italic": false,
              "strikethrough": false,
              "underline": false,
              "code": false,
              "color": "default"
            },
            "plain_text": "Габаритные размеры 12 × 1,5 м",
            "href": null
          }
        ],
        "icon": null,
        "color": "default"
      },
      "children": []
    },
    {
      "id": "0108126c-eadb-42c1-880b-83c8c15461fd",
      "type": "image",
      "content": {
        "caption": [],
        "type": "file",
        "file": {
          "url": "/assets/0108126c-eadb-42c1-880b-83c8c15461fd.webp"
        }
      },
      "children": []
    },
    {
      "id": "8b0133c2-90f7-418a-9bde-efe2b060c820",
      "type": "paragraph",
      "content": {
        "rich_text": [],
        "icon": null,
        "color": "default"
      },
      "children": []
    },
    {
      "id": "30ec6df4-67f8-477c-945f-bbe29f9c9430",
      "type": "paragraph",
      "content": {
        "rich_text": [
          {
            "type": "text",
            "text": {
              "content": "Возможный вариант формирования контейнерной площадки.",
              "link": null
            },
            "annotations": {
              "bold": false,
              "italic": false,
              "strikethrough": false,
              "underline": false,
              "code": false,
              "color": "default"
            },
            "plain_text": "Возможный вариант формирования контейнерной площадки.",
            "href": null
          }
        ],
        "icon": null,
        "color": "default"
      },
      "children": []
    },
    {
      "id": "39991f81-40b8-4f6f-a1eb-ce6109b65e14",
      "type": "paragraph",
      "content": {
        "rich_text": [
          {
            "type": "text",
            "text": {
              "content": "В случае необходимости размещения 10 контейнеров контейнерная площадка должна состоять из 2 блоков.",
              "link": null
            },
            "annotations": {
              "bold": false,
              "italic": false,
              "strikethrough": false,
              "underline": false,
              "code": false,
              "color": "default"
            },
            "plain_text": "В случае необходимости размещения 10 контейнеров контейнерная площадка должна состоять из 2 блоков.",
            "href": null
          }
        ],
        "icon": null,
        "color": "default"
      },
      "children": []
    },
    {
      "id": "2497fc18-a235-4e22-b6d2-5f587992fa1a",
      "type": "image",
      "content": {
        "caption": [],
        "type": "file",
        "file": {
          "url": "/assets/2497fc18-a235-4e22-b6d2-5f587992fa1a.webp"
        }
      },
      "children": []
    },
    {
      "id": 116,
      "type": "heading_1",
      "content": {
        "rich_text": [
          {
            "type": "text",
            "text": {
              "content": "Тип 2. Площадки с заглубленными контейнерами",
              "link": null
            },
            "annotations": {
              "bold": false,
              "italic": false,
              "strikethrough": false,
              "underline": false,
              "code": false,
              "color": "default"
            },
            "plain_text": "Тип 2. Площадки с заглубленными контейнерами",
            "href": null
          }
        ],
        "is_toggleable": false,
        "color": "default"
      },
      "children": []
    },
    {
      "id": "e9ba234f-562a-4949-ae7f-1bf213f5369c",
      "type": "paragraph",
      "content": {
        "rich_text": [
          {
            "type": "text",
            "text": {
              "content": "Для установки на дворовых территориях новых типов застройки.",
              "link": null
            },
            "annotations": {
              "bold": false,
              "italic": false,
              "strikethrough": false,
              "underline": false,
              "code": false,
              "color": "default"
            },
            "plain_text": "Для установки на дворовых территориях новых типов застройки.",
            "href": null
          }
        ],
        "icon": null,
        "color": "default"
      },
      "children": []
    },
    {
      "id": "2ebecb5b-e609-4ab8-b4da-879f5ec0563d",
      "type": "paragraph",
      "content": {
        "rich_text": [
          {
            "type": "text",
            "text": {
              "content": "Рекомендуемое соотношение контейнеров: 70 % контейнеров — для несортируемых отходов, 30 % — для сортируемых отходов.",
              "link": null
            },
            "annotations": {
              "bold": false,
              "italic": false,
              "strikethrough": false,
              "underline": false,
              "code": false,
              "color": "default"
            },
            "plain_text": "Рекомендуемое соотношение контейнеров: 70 % контейнеров — для несортируемых отходов, 30 % — для сортируемых отходов.",
            "href": null
          }
        ],
        "icon": null,
        "color": "default"
      },
      "children": []
    },
    {
      "id": "7f6a4752-0719-489f-a888-d813947ef19a",
      "type": "paragraph",
      "content": {
        "rich_text": [
          {
            "type": "text",
            "text": {
              "content": "Преимущества",
              "link": null
            },
            "annotations": {
              "bold": true,
              "italic": false,
              "strikethrough": false,
              "underline": false,
              "code": false,
              "color": "default"
            },
            "plain_text": "Преимущества",
            "href": null
          }
        ],
        "icon": null,
        "color": "default"
      },
      "children": []
    },
    {
      "type": "bulleted_list_folder",
      "children": [
        {
          "id": "2e17cf63-402b-4244-a36f-a3e4a0c603d8",
          "type": "bulleted_list_item",
          "content": {
            "rich_text": [
              {
                "type": "text",
                "text": {
                  "content": "Отсутствие неприятных запахов",
                  "link": null
                },
                "annotations": {
                  "bold": false,
                  "italic": false,
                  "strikethrough": false,
                  "underline": false,
                  "code": false,
                  "color": "default"
                },
                "plain_text": "Отсутствие неприятных запахов",
                "href": null
              }
            ],
            "color": "default"
          },
          "children": []
        },
        {
          "id": "a650127c-f5ca-443d-9ebd-f433903033a2",
          "type": "bulleted_list_item",
          "content": {
            "rich_text": [
              {
                "type": "text",
                "text": {
                  "content": "Экономия места (большая часть контейнера заглублена)",
                  "link": null
                },
                "annotations": {
                  "bold": false,
                  "italic": false,
                  "strikethrough": false,
                  "underline": false,
                  "code": false,
                  "color": "default"
                },
                "plain_text": "Экономия места (большая часть контейнера заглублена)",
                "href": null
              }
            ],
            "color": "default"
          },
          "children": []
        },
        {
          "id": "bcbdc930-6a32-4db4-99f0-1cf65199c950",
          "type": "bulleted_list_item",
          "content": {
            "rich_text": [
              {
                "type": "text",
                "text": {
                  "content": "Пункты сбора мусора не привлекают животных",
                  "link": null
                },
                "annotations": {
                  "bold": false,
                  "italic": false,
                  "strikethrough": false,
                  "underline": false,
                  "code": false,
                  "color": "default"
                },
                "plain_text": "Пункты сбора мусора не привлекают животных",
                "href": null
              }
            ],
            "color": "default"
          },
          "children": []
        },
        {
          "id": "96d862d3-1be2-4845-a8ea-b3c2502fc438",
          "type": "bulleted_list_item",
          "content": {
            "rich_text": [
              {
                "type": "text",
                "text": {
                  "content": "Чистота и удобство сервисного обслуживания",
                  "link": null
                },
                "annotations": {
                  "bold": false,
                  "italic": false,
                  "strikethrough": false,
                  "underline": false,
                  "code": false,
                  "color": "default"
                },
                "plain_text": "Чистота и удобство сервисного обслуживания",
                "href": null
              }
            ],
            "color": "default"
          },
          "children": []
        },
        {
          "id": "089eedb4-436b-4d4f-b5f5-717a09a0585f",
          "type": "bulleted_list_item",
          "content": {
            "rich_text": [
              {
                "type": "text",
                "text": {
                  "content": "Минимальная опасность возгорания",
                  "link": null
                },
                "annotations": {
                  "bold": false,
                  "italic": false,
                  "strikethrough": false,
                  "underline": false,
                  "code": false,
                  "color": "default"
                },
                "plain_text": "Минимальная опасность возгорания",
                "href": null
              }
            ],
            "color": "default"
          },
          "children": []
        },
        {
          "id": "cf6cf50a-d8b6-4dee-ab93-c6620042f3d0",
          "type": "bulleted_list_item",
          "content": {
            "rich_text": [
              {
                "type": "text",
                "text": {
                  "content": "Долговечность контейнера",
                  "link": null
                },
                "annotations": {
                  "bold": false,
                  "italic": false,
                  "strikethrough": false,
                  "underline": false,
                  "code": false,
                  "color": "default"
                },
                "plain_text": "Долговечность контейнера",
                "href": null
              }
            ],
            "color": "default"
          },
          "children": []
        },
        {
          "id": "758b7dfd-1870-4839-b6f7-692663077b46",
          "type": "bulleted_list_item",
          "content": {
            "rich_text": [
              {
                "type": "text",
                "text": {
                  "content": "Эстетичность",
                  "link": null
                },
                "annotations": {
                  "bold": false,
                  "italic": false,
                  "strikethrough": false,
                  "underline": false,
                  "code": false,
                  "color": "default"
                },
                "plain_text": "Эстетичность",
                "href": null
              }
            ],
            "color": "default"
          },
          "children": []
        }
      ]
    },
    {
      "id": "542d9444-d209-4312-a472-8916468e73fc",
      "type": "paragraph",
      "content": {
        "rich_text": [],
        "icon": null,
        "color": "default"
      },
      "children": []
    },
    {
      "id": "a5199e27-da6e-49a4-998f-a2b5dadc57b6",
      "type": "paragraph",
      "content": {
        "rich_text": [
          {
            "type": "text",
            "text": {
              "content": "Габаритные размеры 7 × 2,7 м",
              "link": null
            },
            "annotations": {
              "bold": false,
              "italic": false,
              "strikethrough": false,
              "underline": false,
              "code": false,
              "color": "default"
            },
            "plain_text": "Габаритные размеры 7 × 2,7 м",
            "href": null
          }
        ],
        "icon": null,
        "color": "default"
      },
      "children": []
    },
    {
      "id": "322f3559-0412-490c-a91f-867ae773f640",
      "type": "image",
      "content": {
        "caption": [],
        "type": "file",
        "file": {
          "url": "/assets/322f3559-0412-490c-a91f-867ae773f640.webp"
        }
      },
      "children": []
    },
    {
      "id": "85aa846f-2045-40be-b445-4d2290015022",
      "type": "paragraph",
      "content": {
        "rich_text": [],
        "icon": null,
        "color": "default"
      },
      "children": []
    },
    {
      "id": "f2f15b7a-cde3-4197-9ad3-973a3ee87019",
      "type": "paragraph",
      "content": {
        "rich_text": [
          {
            "type": "text",
            "text": {
              "content": "Габаритные размеры 9,2 × 2,7 м",
              "link": null
            },
            "annotations": {
              "bold": false,
              "italic": false,
              "strikethrough": false,
              "underline": false,
              "code": false,
              "color": "default"
            },
            "plain_text": "Габаритные размеры 9,2 × 2,7 м",
            "href": null
          }
        ],
        "icon": null,
        "color": "default"
      },
      "children": []
    },
    {
      "id": "c91fec5b-3cc3-49e5-9e3d-474fd1ed1875",
      "type": "image",
      "content": {
        "caption": [],
        "type": "file",
        "file": {
          "url": "/assets/c91fec5b-3cc3-49e5-9e3d-474fd1ed1875.webp"
        }
      },
      "children": []
    },
    {
      "id": "3a386757-1ee4-4f88-957e-72af999685ea",
      "type": "paragraph",
      "content": {
        "rich_text": [],
        "icon": null,
        "color": "default"
      },
      "children": []
    },
    {
      "id": "9011a312-c1d7-4b4b-9b31-64a6b1c430a0",
      "type": "paragraph",
      "content": {
        "rich_text": [
          {
            "type": "text",
            "text": {
              "content": "с заглубленными контейнерами 9,2 × 2,7 м с частичным ограждением",
              "link": null
            },
            "annotations": {
              "bold": false,
              "italic": false,
              "strikethrough": false,
              "underline": false,
              "code": false,
              "color": "default"
            },
            "plain_text": "с заглубленными контейнерами 9,2 × 2,7 м с частичным ограждением",
            "href": null
          }
        ],
        "icon": null,
        "color": "default"
      },
      "children": []
    },
    {
      "id": "0568fc97-4d4b-43ff-a36a-cc4254ad2919",
      "type": "image",
      "content": {
        "caption": [],
        "type": "file",
        "file": {
          "url": "/assets/0568fc97-4d4b-43ff-a36a-cc4254ad2919.webp"
        }
      },
      "children": []
    },
    {
      "id": 117,
      "type": "heading_1",
      "content": {
        "rich_text": [
          {
            "type": "text",
            "text": {
              "content": "Тип 3. Площадки закрытого типа с откатными контейнерами",
              "link": null
            },
            "annotations": {
              "bold": false,
              "italic": false,
              "strikethrough": false,
              "underline": false,
              "code": false,
              "color": "default"
            },
            "plain_text": "Тип 3. Площадки закрытого типа с откатными контейнерами",
            "href": null
          }
        ],
        "is_toggleable": false,
        "color": "default"
      },
      "children": []
    },
    {
      "id": "c692b3b5-30f9-40f7-ad2b-435f0ffe9c74",
      "type": "paragraph",
      "content": {
        "rich_text": [
          {
            "type": "text",
            "text": {
              "content": "Для установки на дворовых территориях, имеющих малую площадь, при отсутствии возможности соблюдения нормативных расстояний. Рекомендуемое соотношение контейнеров: 70 % контейнеров — для несортируемых отходов, 30 % — для сортируемых отходов",
              "link": null
            },
            "annotations": {
              "bold": false,
              "italic": false,
              "strikethrough": false,
              "underline": false,
              "code": false,
              "color": "default"
            },
            "plain_text": "Для установки на дворовых территориях, имеющих малую площадь, при отсутствии возможности соблюдения нормативных расстояний. Рекомендуемое соотношение контейнеров: 70 % контейнеров — для несортируемых отходов, 30 % — для сортируемых отходов",
            "href": null
          }
        ],
        "icon": null,
        "color": "default"
      },
      "children": []
    },
    {
      "id": "2a080be8-b034-4f64-ab82-012573731646",
      "type": "paragraph",
      "content": {
        "rich_text": [
          {
            "type": "text",
            "text": {
              "content": "Преимущества",
              "link": null
            },
            "annotations": {
              "bold": true,
              "italic": false,
              "strikethrough": false,
              "underline": false,
              "code": false,
              "color": "default"
            },
            "plain_text": "Преимущества",
            "href": null
          },
          {
            "type": "text",
            "text": {
              "content": " ",
              "link": null
            },
            "annotations": {
              "bold": false,
              "italic": false,
              "strikethrough": false,
              "underline": false,
              "code": false,
              "color": "default"
            },
            "plain_text": " ",
            "href": null
          }
        ],
        "icon": null,
        "color": "default"
      },
      "children": []
    },
    {
      "type": "bulleted_list_folder",
      "children": [
        {
          "id": "852d0e53-7e8c-4371-8409-2aa8a60f6458",
          "type": "bulleted_list_item",
          "content": {
            "rich_text": [
              {
                "type": "text",
                "text": {
                  "content": "Наличие навеса",
                  "link": null
                },
                "annotations": {
                  "bold": false,
                  "italic": false,
                  "strikethrough": false,
                  "underline": false,
                  "code": false,
                  "color": "default"
                },
                "plain_text": "Наличие навеса",
                "href": null
              }
            ],
            "color": "default"
          },
          "children": []
        },
        {
          "id": "21a617ba-7efd-4993-a70b-189087fd0c0c",
          "type": "bulleted_list_item",
          "content": {
            "rich_text": [
              {
                "type": "text",
                "text": {
                  "content": "Эстетичность",
                  "link": null
                },
                "annotations": {
                  "bold": false,
                  "italic": false,
                  "strikethrough": false,
                  "underline": false,
                  "code": false,
                  "color": "default"
                },
                "plain_text": "Эстетичность",
                "href": null
              }
            ],
            "color": "default"
          },
          "children": []
        },
        {
          "id": "ec5d7bba-519a-4000-aa9e-0cefa396c8c9",
          "type": "bulleted_list_item",
          "content": {
            "rich_text": [
              {
                "type": "text",
                "text": {
                  "content": "Возможность ограничения доступа посторонним",
                  "link": null
                },
                "annotations": {
                  "bold": false,
                  "italic": false,
                  "strikethrough": false,
                  "underline": false,
                  "code": false,
                  "color": "default"
                },
                "plain_text": "Возможность ограничения доступа посторонним",
                "href": null
              }
            ],
            "color": "default"
          },
          "children": []
        }
      ]
    },
    {
      "id": "063a01a3-e652-48e5-bded-e80d3f7e2a9f",
      "type": "paragraph",
      "content": {
        "rich_text": [],
        "icon": null,
        "color": "default"
      },
      "children": []
    },
    {
      "id": "93ffdad6-20f7-4228-8fb5-e998494a2ab7",
      "type": "paragraph",
      "content": {
        "rich_text": [
          {
            "type": "text",
            "text": {
              "content": "Габаритные размеры 7 × 2,9 м",
              "link": null
            },
            "annotations": {
              "bold": false,
              "italic": false,
              "strikethrough": false,
              "underline": false,
              "code": false,
              "color": "default"
            },
            "plain_text": "Габаритные размеры 7 × 2,9 м",
            "href": null
          }
        ],
        "icon": null,
        "color": "default"
      },
      "children": []
    },
    {
      "id": "09583f75-2f7c-4f1e-8db3-b80da9aa82c8",
      "type": "image",
      "content": {
        "caption": [],
        "type": "file",
        "file": {
          "url": "/assets/09583f75-2f7c-4f1e-8db3-b80da9aa82c8.webp"
        }
      },
      "children": []
    },
    {
      "id": "97b5efd3-9131-4e38-82b0-993012b7493c",
      "type": "paragraph",
      "content": {
        "rich_text": [],
        "icon": null,
        "color": "default"
      },
      "children": []
    },
    {
      "id": "81e8ab00-d3af-42db-baad-488af875dcfd",
      "type": "image",
      "content": {
        "caption": [],
        "type": "file",
        "file": {
          "url": "/assets/81e8ab00-d3af-42db-baad-488af875dcfd.webp"
        }
      },
      "children": []
    },
    {
      "id": 118,
      "type": "heading_1",
      "content": {
        "rich_text": [
          {
            "type": "text",
            "text": {
              "content": "Тип 4. Площадки полуоткрытого типа с откатными контейнерами",
              "link": null
            },
            "annotations": {
              "bold": false,
              "italic": false,
              "strikethrough": false,
              "underline": false,
              "code": false,
              "color": "default"
            },
            "plain_text": "Тип 4. Площадки полуоткрытого типа с откатными контейнерами",
            "href": null
          }
        ],
        "is_toggleable": false,
        "color": "default"
      },
      "children": []
    },
    {
      "id": "1316e91d-8a36-4041-a865-bc9d19a3cfc4",
      "type": "paragraph",
      "content": {
        "rich_text": [
          {
            "type": "text",
            "text": {
              "content": "Для установки на дворовых территориях сложившейся застройки. Рекомендуемое соотношение контейнеров: 70 % контейнеров — для несортируемых отходов, 30 % — для сортируемых отходов.",
              "link": null
            },
            "annotations": {
              "bold": false,
              "italic": false,
              "strikethrough": false,
              "underline": false,
              "code": false,
              "color": "default"
            },
            "plain_text": "Для установки на дворовых территориях сложившейся застройки. Рекомендуемое соотношение контейнеров: 70 % контейнеров — для несортируемых отходов, 30 % — для сортируемых отходов.",
            "href": null
          }
        ],
        "icon": null,
        "color": "default"
      },
      "children": []
    },
    {
      "id": "1312bfda-c53e-412d-9655-3f10f1c2d28d",
      "type": "paragraph",
      "content": {
        "rich_text": [
          {
            "type": "text",
            "text": {
              "content": "Преимущества",
              "link": null
            },
            "annotations": {
              "bold": true,
              "italic": false,
              "strikethrough": false,
              "underline": false,
              "code": false,
              "color": "default"
            },
            "plain_text": "Преимущества",
            "href": null
          }
        ],
        "icon": null,
        "color": "default"
      },
      "children": []
    },
    {
      "type": "bulleted_list_folder",
      "children": [
        {
          "id": "df784b65-3b42-4c4f-b69a-307f2c96c172",
          "type": "bulleted_list_item",
          "content": {
            "rich_text": [
              {
                "type": "text",
                "text": {
                  "content": "Наличие навеса",
                  "link": null
                },
                "annotations": {
                  "bold": false,
                  "italic": false,
                  "strikethrough": false,
                  "underline": false,
                  "code": false,
                  "color": "default"
                },
                "plain_text": "Наличие навеса",
                "href": null
              }
            ],
            "color": "default"
          },
          "children": []
        },
        {
          "id": "12f99330-41c6-49ed-a769-f52eb228f085",
          "type": "bulleted_list_item",
          "content": {
            "rich_text": [
              {
                "type": "text",
                "text": {
                  "content": "Эстетичность",
                  "link": null
                },
                "annotations": {
                  "bold": false,
                  "italic": false,
                  "strikethrough": false,
                  "underline": false,
                  "code": false,
                  "color": "default"
                },
                "plain_text": "Эстетичность",
                "href": null
              }
            ],
            "color": "default"
          },
          "children": []
        },
        {
          "id": "76cb082a-d5ec-4498-82b7-c043c86ec33a",
          "type": "bulleted_list_item",
          "content": {
            "rich_text": [
              {
                "type": "text",
                "text": {
                  "content": "Возможность ограничения доступа посторонним",
                  "link": null
                },
                "annotations": {
                  "bold": false,
                  "italic": false,
                  "strikethrough": false,
                  "underline": false,
                  "code": false,
                  "color": "default"
                },
                "plain_text": "Возможность ограничения доступа посторонним",
                "href": null
              }
            ],
            "color": "default"
          },
          "children": []
        }
      ]
    },
    {
      "id": "180ac150-d9f2-42dd-9201-a4faa7738219",
      "type": "paragraph",
      "content": {
        "rich_text": [],
        "icon": null,
        "color": "default"
      },
      "children": []
    },
    {
      "id": "57ef9310-09bc-433d-956b-63dba8f0e176",
      "type": "paragraph",
      "content": {
        "rich_text": [
          {
            "type": "text",
            "text": {
              "content": "Габаритные размеры 8 × 1,5 м",
              "link": null
            },
            "annotations": {
              "bold": false,
              "italic": false,
              "strikethrough": false,
              "underline": false,
              "code": false,
              "color": "default"
            },
            "plain_text": "Габаритные размеры 8 × 1,5 м",
            "href": null
          }
        ],
        "icon": null,
        "color": "default"
      },
      "children": []
    },
    {
      "id": "65e8dcb6-2c66-404b-8def-e23a94f32382",
      "type": "image",
      "content": {
        "caption": [],
        "type": "file",
        "file": {
          "url": "/assets/65e8dcb6-2c66-404b-8def-e23a94f32382.webp"
        }
      },
      "children": []
    },
    {
      "id": "fc7430d9-0edc-43fc-bce8-381c237a9a4d",
      "type": "paragraph",
      "content": {
        "rich_text": [],
        "icon": null,
        "color": "default"
      },
      "children": []
    },
    {
      "id": "5f83cba7-648a-4ea6-b721-7323d5894f27",
      "type": "paragraph",
      "content": {
        "rich_text": [
          {
            "type": "text",
            "text": {
              "content": "Габаритные размеры 8,5 × 1,5 м",
              "link": null
            },
            "annotations": {
              "bold": false,
              "italic": false,
              "strikethrough": false,
              "underline": false,
              "code": false,
              "color": "default"
            },
            "plain_text": "Габаритные размеры 8,5 × 1,5 м",
            "href": null
          }
        ],
        "icon": null,
        "color": "default"
      },
      "children": []
    },
    {
      "id": "0b9baf60-11b5-462a-96cf-e8ab229f9218",
      "type": "image",
      "content": {
        "caption": [],
        "type": "file",
        "file": {
          "url": "/assets/0b9baf60-11b5-462a-96cf-e8ab229f9218.webp"
        }
      },
      "children": []
    }
  ],
  "node_properties": {
    "properties": {
      "Name": {
        "id": "title",
        "type": "title",
        "title": [
          {
            "type": "text",
            "text": {
              "content": "Типология контейнерных площадок твердых коммунальных отходов",
              "link": null
            },
            "annotations": {
              "bold": false,
              "italic": false,
              "strikethrough": false,
              "underline": false,
              "code": false,
              "color": "default"
            },
            "plain_text": "Типология контейнерных площадок твердых коммунальных отходов",
            "href": null
          }
        ]
      },
      "order": {
        "id": "cbcq",
        "type": "number",
        "number": 2
      },
      "pageUrl": {
        "id": "VfY_",
        "type": "url",
        "url": "typology"
      }
    },
    "cover": null
  }
}